{"cameraMode":{"drawMode":0,"name":"Shaded","section":"Shading Mode"},"sceneLighting":true,"audioPlay":false,"sceneViewState":{"m_AlwaysRefresh":false,"showFog":true,"showSkybox":true,"showFlares":true,"showImageEffects":true,"showParticleSystems":true,"showVisualEffectGraphs":true,"m_FxEnabled":true},"in2DMode":false,"pivot":{"x":18.328411102294923,"y":6.114203929901123,"z":-3.6840341091156008},"rotation":{"x":0.08975045382976532,"y":0.5997623801231384,"z":-0.06795286387205124,"w":0.7922495007514954},"size":12.12435531616211,"orthographic":false}